mesh_aws_client/__init__.py
mesh_aws_client/mesh_check_send_parameters_application.py
mesh_aws_client/mesh_common.py
mesh_aws_client/mesh_fetch_message_chunk_application.py
mesh_aws_client/mesh_mailbox.py
mesh_aws_client/mesh_poll_mailbox_application.py
mesh_aws_client/mesh_send_message_chunk_application.py
spine_aws_common/__init__.py
spine_aws_common/alb_application.py
spine_aws_common/api_gateway_application.py
spine_aws_common/api_gateway_v2_application.py
spine_aws_common/batch_application.py
spine_aws_common/cloudlogbase.cfg
spine_aws_common/cloudwatch_logs_application.py
spine_aws_common/dynamodb_streams_application.py
spine_aws_common/eventbridge_application.py
spine_aws_common/kinesis_stream_application.py
spine_aws_common/lambda_application.py
spine_aws_common/logger.py
spine_aws_common/s3_event_application.py
spine_aws_common/s3_object_event_application.py
spine_aws_common/ses_application.py
spine_aws_common/sns_application.py
spine_aws_common/sqs_application.py
spine_aws_common/utilities.py
spine_aws_common/web_application.py
spine_aws_common/log/__init__.py
spine_aws_common/log/constants.py
spine_aws_common/log/details.py
spine_aws_common/log/formatting.py
spine_aws_common/log/log_helper.py
spine_aws_common/log/loglineprocessor.py
spine_aws_common/log/logutil.py
spine_aws_common/log/masking.py
spine_aws_common/log/spinelogging.py
spine_aws_common/log/thirdpartylogging.py
spine_aws_common/log/writer.py
spine_aws_common-0.2.14.dist-info/METADATA
spine_aws_common-0.2.14.dist-info/WHEEL
spine_aws_common-0.2.14.dist-info/top_level.txt
spine_aws_common-0.2.14.dist-info/RECORD
