Metadata-Version: 2.1
Name: spine-aws-common
Version: 0.2.14
Summary: NHS Digital Spine Core common AWS code
Home-page: https://github.com/NHSDigital/spine-core-aws-common
Author: NHS Digital
Author-email: devops.core@nhs.net
Project-URL: Bug Tracker, https://github.com/NHSDigital/spine-core-aws-common/issues
Classifier: Programming Language :: Python :: 3
Classifier: License :: OSI Approved :: MIT License
Classifier: Operating System :: OS Independent
Requires-Python: >=3.6
Requires-Dist: six
Requires-Dist: aws-lambda-powertools
